{
  "part_id": "corner019",
  "thickness": 1.78 ,
  "circular_holes": [
    {
      "name": "CIRC_HOLE_0",
      "type": "circular_hole",
      "radius": 2.159,
      "center": [
        -0.796227,
        -0.0,
        54.6608
      ],
      "normal": [
        1.0,
        -0.0,
        -6.017286329656971e-16
      ],
      "area": 2.516992,
      "num_faces": 2,
      "faces": [
        {
          "face_id": 0,
          "center": [
            -0.796227,
            -1.374462,
            54.6608
          ],
          "area": 1.258496,
          "angle_span": 180.0,
          "normal": [
            0,
            0,
            0
          ]
        },
        {
          "face_id": 8,
          "center": [
            -0.796227,
            1.374462,
            54.6608
          ],
          "area": 1.258496,
          "angle_span": 180.0,
          "normal": [
            0,
            0,
            0
          ]
        }
      ]
    },
    {
      "name": "CIRC_HOLE_1",
      "type": "circular_hole",
      "radius": 2.159,
      "center": [
        -0.796227,
        -0.0,
        19.6088
      ],
      "normal": [
        1.0,
        -0.0,
        -6.017286329656971e-16
      ],
      "area": 2.516992,
      "num_faces": 2,
      "faces": [
        {
          "face_id": 1,
          "center": [
            -0.796227,
            -1.374462,
            19.6088
          ],
          "area": 1.258496,
          "angle_span": 180.0,
          "normal": [
            0,
            0,
            0
          ]
        },
        {
          "face_id": 7,
          "center": [
            -0.796227,
            1.374462,
            19.6088
          ],
          "area": 1.258496,
          "angle_span": 180.0,
          "normal": [
            0,
            0,
            0
          ]
        }
      ]
    },
    {
      "name": "CIRC_HOLE_2",
      "type": "circular_hole",
      "radius": 2.159,
      "center": [
        54.6608,
        -0.0,
        -0.796227
      ],
      "normal": [
        -0.0,
        -0.0,
        1.0
      ],
      "area": 2.516992,
      "num_faces": 2,
      "faces": [
        {
          "face_id": 2,
          "center": [
            54.6608,
            -1.374462,
            -0.796227
          ],
          "area": 1.258496,
          "angle_span": 180.0,
          "normal": [
            0,
            0,
            0
          ]
        },
        {
          "face_id": 6,
          "center": [
            54.6608,
            1.374462,
            -0.796227
          ],
          "area": 1.258496,
          "angle_span": 180.0,
          "normal": [
            0,
            0,
            0
          ]
        }
      ]
    },
    {
      "name": "CIRC_HOLE_3",
      "type": "circular_hole",
      "radius": 2.159,
      "center": [
        19.6088,
        -0.0,
        -0.796227
      ],
      "normal": [
        -0.0,
        -0.0,
        1.0
      ],
      "area": 2.516992,
      "num_faces": 2,
      "faces": [
        {
          "face_id": 3,
          "center": [
            19.6088,
            -1.374462,
            -0.796227
          ],
          "area": 1.258496,
          "angle_span": 180.0,
          "normal": [
            0,
            0,
            0
          ]
        },
        {
          "face_id": 5,
          "center": [
            19.6088,
            1.374462,
            -0.796227
          ],
          "area": 1.258496,
          "angle_span": 180.0,
          "normal": [
            0,
            0,
            0
          ]
        }
      ]
    }
  ],
  "fillets": [
    {
      "name": "FILLET_0",
      "type": "internal_fillet",
      "radius": 1.3335,
      "center": [
        1.373568,
        0.0,
        1.373568
      ],
      "normal": [
        0.0,
        1.0,
        0.0
      ],
      "axis_direction": [
        0.0,
        1.0,
        0.0
      ],
      "axis_location": [
        2.2225,
        7.493,
        2.2225
      ],
      "area": 31.390528,
      "num_faces": 1,
      "total_angle": 90.0,
      "faces": [
        {
          "face_id": 0,
          "center": [
            1.373568,
            0.0,
            1.373568
          ],
          "area": 31.390528,
          "angle_span": 90.0,
          "normal": [
            0.0,
            1.0,
            0.0
          ]
        }
      ]
    },
    {
      "name": "FILLET_1",
      "type": "external_fillet",
      "radius": 2.667,
      "center": [
        0.080135,
        -0.0,
        0.080135
      ],
      "normal": [
        0.0,
        -1.0,
        0.0
      ],
      "axis_direction": [
        0.0,
        -1.0,
        0.0
      ],
      "axis_location": [
        1.778,
        7.493,
        1.778
      ],
      "area": 62.781057,
      "num_faces": 1,
      "total_angle": 90.0,
      "faces": [
        {
          "face_id": 1,
          "center": [
            0.080135,
            -0.0,
            0.080135
          ],
          "area": 62.781057,
          "angle_span": 90.0,
          "normal": [
            0.0,
            -1.0,
            0.0
          ]
        }
      ]
    }
  ],
  "faces": [
    {
      "name": "FACE_0",
      "face_id": 0,
      "center": [
        0.09277250694193012,
        -1.7716499999999997,
        19.60880000000001
      ],
      "normal": [
        -0.6560590289905084,
        -0.754709580222771,
        5.334074034151101e-16
      ],
      "area": 18.899801419293755
    },
    {
      "name": "FACE_1",
      "face_id": 1,
      "center": [
        0.092772506941951,
        -1.7716500000000002,
        54.6608
      ],
      "normal": [
        -0.6560590289905084,
        -0.7547095802227709,
        5.334074034151101e-16
      ],
      "area": 18.899801419293773
    },
    {
      "name": "FACE_2",
      "face_id": 2,
      "center": [
        -0.7962274930580326,
        -1.0795000000000003,
        54.6608
      ],
      "normal": [
        1.10535756647513e-31,
        -1.0,
        1.8369701987210297e-16
      ],
      "area": 1.2584958946079043
    },
    {
      "name": "FACE_3",
      "face_id": 3,
      "center": [
        -0.7962274930580432,
        -1.0795000000000003,
        19.60880000000001
      ],
      "normal": [
        1.10535756647513e-31,
        -1.0,
        1.8369701987210297e-16
      ],
      "area": 1.258495894607762
    },
    {
      "name": "FACE_4",
      "face_id": 4,
      "center": [
        19.60880000000001,
        -1.7716499999999957,
        0.09277250694201777
      ],
      "normal": [
        -1.3863790075584886e-16,
        -0.7547095802227711,
        -0.6560590289905084
      ],
      "area": 18.899801419293645
    },
    {
      "name": "FACE_5",
      "face_id": 5,
      "center": [
        54.6608,
        -1.7716499999999966,
        0.09277250694201933
      ],
      "normal": [
        -1.3863790075584886e-16,
        -0.754709580222771,
        -0.6560590289905084
      ],
      "area": 18.89980141929362
    },
    {
      "name": "FACE_6",
      "face_id": 6,
      "center": [
        54.6608,
        -1.0795000000000003,
        -0.796227493057998
      ],
      "normal": [
        -1.8369701987210297e-16,
        -1.0,
        -0.0
      ],
      "area": 1.2584958946084193
    },
    {
      "name": "FACE_7",
      "face_id": 7,
      "center": [
        19.60880000000001,
        -1.0795000000000003,
        -0.796227493057998
      ],
      "normal": [
        -1.8369701987210297e-16,
        -1.0,
        -0.0
      ],
      "area": 1.2584958946084186
    },
    {
      "name": "FACE_8",
      "face_id": 8,
      "center": [
        -0.8889999999999981,
        0.0,
        32.1945
      ],
      "normal": [
        1.0,
        -0.0,
        0.0
      ],
      "area": 882.3556457081645
    },
    {
      "name": "FACE_9",
      "face_id": 9,
      "center": [
        3.885780586188048e-15,
        0.0,
        62.61099999999999
      ],
      "normal": [
        0.0,
        0.0,
        -1.0
      ],
      "area": 26.645108000000057
    },
    {
      "name": "FACE_10",
      "face_id": 10,
      "center": [
        0.8889999999999723,
        0.0,
        32.416750000000015
      ],
      "normal": [
        -1.0,
        0.0,
        1.1119211548286264e-15
      ],
      "area": 826.0968272391425
    },
    {
      "name": "FACE_11",
      "face_id": 11,
      "center": [
        32.416749999999965,
        0.0,
        0.8890000000000151
      ],
      "normal": [
        -5.691349986800542e-16,
        0.0,
        -1.0
      ],
      "area": 826.0968272391443
    },
    {
      "name": "FACE_12",
      "face_id": 12,
      "center": [
        62.61099999999999,
        0.0,
        -2.4424906541753444e-15
      ],
      "normal": [
        -1.0,
        0.0,
        0.0
      ],
      "area": 26.645107999999986
    },
    {
      "name": "FACE_13",
      "face_id": 13,
      "center": [
        32.1945,
        0.0,
        -0.889000000000002
      ],
      "normal": [
        3.414809992080329e-18,
        -0.0,
        1.0
      ],
      "area": 882.3556457081644
    },
    {
      "name": "FACE_14",
      "face_id": 14,
      "center": [
        30.860999999999997,
        7.492999999999999,
        30.860999999999994
      ],
      "normal": [
        0.0,
        -1.0,
        0.0
      ],
      "area": 221.499886717786
    },
    {
      "name": "FACE_15",
      "face_id": 15,
      "center": [
        30.860999999999997,
        -7.492999999999999,
        30.860999999999994
      ],
      "normal": [
        0.0,
        -1.0,
        0.0
      ],
      "area": 221.49988671778635
    },
    {
      "name": "FACE_16",
      "face_id": 16,
      "center": [
        1.5557499999999396,
        0.0,
        1.555750000000032
      ],
      "normal": [
        -0.7071067811865477,
        0.0,
        -0.7071067811865474
      ],
      "area": 31.390528330089992
    },
    {
      "name": "FACE_17",
      "face_id": 17,
      "center": [
        0.4445000000000014,
        0.0,
        0.44450000000000195
      ],
      "normal": [
        -0.7071067811865477,
        -0.0,
        -0.7071067811865474
      ],
      "area": 62.78105666017997
    },
    {
      "name": "FACE_18",
      "face_id": 18,
      "center": [
        19.60880000000001,
        1.0795000000000006,
        -0.796227493057998
      ],
      "normal": [
        6.123233995736766e-17,
        1.0,
        0.0
      ],
      "area": 1.2584958946084186
    },
    {
      "name": "FACE_19",
      "face_id": 19,
      "center": [
        54.6608,
        1.0795000000000006,
        -0.796227493057998
      ],
      "normal": [
        6.123233995736766e-17,
        1.0,
        0.0
      ],
      "area": 1.2584958946084193
    },
    {
      "name": "FACE_20",
      "face_id": 20,
      "center": [
        54.6608,
        1.7716499999999968,
        0.09277250694201933
      ],
      "normal": [
        4.621263358528295e-17,
        0.754709580222771,
        -0.6560590289905084
      ],
      "area": 18.899801419293624
    },
    {
      "name": "FACE_21",
      "face_id": 21,
      "center": [
        19.60880000000001,
        1.771649999999996,
        0.09277250694201777
      ],
      "normal": [
        4.6212633585282956e-17,
        0.7547095802227711,
        -0.6560590289905084
      ],
      "area": 18.89980141929365
    },
    {
      "name": "FACE_22",
      "face_id": 22,
      "center": [
        -0.7962274930580432,
        1.0795000000000006,
        19.60880000000001
      ],
      "normal": [
        -3.6845252215837674e-32,
        1.0,
        -6.123233995736766e-17
      ],
      "area": 1.258495894607762
    },
    {
      "name": "FACE_23",
      "face_id": 23,
      "center": [
        -0.7962274930580326,
        1.0795000000000006,
        54.6608
      ],
      "normal": [
        -3.6845252215837674e-32,
        1.0,
        -6.123233995736766e-17
      ],
      "area": 1.2584958946079041
    },
    {
      "name": "FACE_24",
      "face_id": 24,
      "center": [
        0.092772506941951,
        1.7716500000000004,
        54.6608
      ],
      "normal": [
        -0.6560590289905084,
        0.7547095802227709,
        3.485568690739783e-16
      ],
      "area": 18.899801419293745
    },
    {
      "name": "FACE_25",
      "face_id": 25,
      "center": [
        0.09277250694193012,
        1.77165,
        19.60880000000001
      ],
      "normal": [
        -0.6560590289905084,
        0.754709580222771,
        3.485568690739783e-16
      ],
      "area": 18.89980141929378
    }
  ]
}